dlpytools/__init__.py
dlpytools/stk.py
dlpytools/tools.py
dlpytools-0.1.2.dist-info/LICENSE
dlpytools-0.1.2.dist-info/METADATA
dlpytools-0.1.2.dist-info/WHEEL
dlpytools-0.1.2.dist-info/top_level.txt
dlpytools-0.1.2.dist-info/RECORD
