Metadata-Version: 2.1
Name: dlpytools
Version: 0.1.2
Summary: common tools
Home-page: https://github.com/GuNanHai/dltools
Author: guhai
Author-email: bysideen@gmail.com
License: MIT License
Keywords: tools
Platform: any
